obp_accounting_sdk/__init__.py
obp_accounting_sdk/_version.py
obp_accounting_sdk/constants.py
obp_accounting_sdk/errors.py
obp_accounting_sdk/utils.py
obp_accounting_sdk/_async/__init__.py
obp_accounting_sdk/_async/factory.py
obp_accounting_sdk/_async/longrun.py
obp_accounting_sdk/_async/oneshot.py
obp_accounting_sdk/_sync/__init__.py
obp_accounting_sdk/_sync/factory.py
obp_accounting_sdk/_sync/longrun.py
obp_accounting_sdk/_sync/oneshot.py
obp_accounting_sdk-0.5.0.dist-info/licenses/AUTHORS.txt
obp_accounting_sdk-0.5.0.dist-info/licenses/LICENSE.txt
obp_accounting_sdk-0.5.0.dist-info/METADATA
obp_accounting_sdk-0.5.0.dist-info/WHEEL
obp_accounting_sdk-0.5.0.dist-info/top_level.txt
obp_accounting_sdk-0.5.0.dist-info/RECORD
