Metadata-Version: 2.4
Name: obp-accounting-sdk
Version: 0.5.0
Summary: Python SDK for the OBP Accounting Service.
Author: Blue Brain Project, EPFL, Open Brain Institute
License: Apache-2.0
Project-URL: Homepage, https://github.com/openbraininstitute/accounting-sdk
Project-URL: Repository, https://github.com/openbraininstitute/accounting-sdk.git
Project-URL: Tracker, https://github.com/openbraininstitute/accounting-sdk/issues
Classifier: Development Status :: 2 - Pre-Alpha
Classifier: Programming Language :: Python
Classifier: Programming Language :: Python :: 3
Classifier: Programming Language :: Python :: 3.11
Classifier: Programming Language :: Python :: 3.12
Classifier: Programming Language :: Python :: 3.13
Requires-Python: >=3.11
License-File: LICENSE.txt
License-File: AUTHORS.txt
Requires-Dist: httpx
Dynamic: license-file
